{"availableLanguageIds": ["pt_BR"], "contentType": "journal", "dataDefinitionFields": [{"customProperties": {"labelAtStructureLevel": true, "ddmStructureLayoutId": "", "ddmStructureId": "", "upgradedStructure": false, "fieldReference": "Fieldset96148159", "rows": [{"columns":[{"size":12,"fields":["Text78260527"]}]},{"columns":[{"size":12,"fields":["Image25921635"]}]},{"columns":[{"size":12,"fields":["Text81373875"]}]}], "collapsible": false}, "defaultValue": {}, "fieldType": "fieldset", "indexable": false, "label": {"pt_BR": "Grupo de campos"}, "localizable": false, "name": "Fieldset96148159", "nestedDataDefinitionFields": [{"customProperties": {"labelAtStructureLevel": true, "confirmationErrorMessage": {"pt_BR": ""}, "hideField": false, "autocomplete": false, "ddmDataProviderInstanceId": [], "dataType": "string", "tooltip": {"pt_BR": ""}, "requireConfirmation": false, "displayStyle": "singleline", "fieldNamespace": "", "requiredErrorMessage": {"pt_BR": ""}, "visibilityExpression": "", "objectFieldName": "", "ddmDataProviderInstanceOutput": [], "options": {"pt_BR": [{"reference":"Opção66908124","label":"Opção","value":"Opção66908124"}]}, "nativeField": false, "confirmationLabel": {"pt_BR": ""}, "fieldReference": "Text78260527", "placeholder": {"pt_BR": ""}, "dataSourceType": "manual", "direction": ["vertical"]}, "defaultValue": {"pt_BR": ""}, "fieldType": "text", "indexType": "keyword", "indexable": true, "label": {"pt_BR": "Titulo"}, "localizable": true, "name": "Text78260527", "nestedDataDefinitionFields": [], "readOnly": false, "repeatable": false, "required": false, "showLabel": true, "tip": {"pt_BR": ""}}, {"customProperties": {"fieldNamespace": "", "requiredErrorMessage": {"pt_BR": ""}, "visibilityExpression": "", "objectFieldName": "", "dataType": "image", "requiredDescription": true, "fieldReference": "Image25921635"}, "defaultValue": {"pt_BR": {}}, "fieldType": "image", "indexType": "text", "indexable": true, "label": {"pt_BR": "Imagem"}, "localizable": true, "name": "Image25921635", "nestedDataDefinitionFields": [], "readOnly": false, "repeatable": false, "required": false, "showLabel": true, "tip": {"pt_BR": ""}}, {"customProperties": {"labelAtStructureLevel": true, "confirmationErrorMessage": {"pt_BR": ""}, "hideField": false, "autocomplete": false, "ddmDataProviderInstanceId": [], "dataType": "string", "tooltip": {"pt_BR": ""}, "requireConfirmation": false, "displayStyle": "singleline", "fieldNamespace": "", "requiredErrorMessage": {"pt_BR": ""}, "visibilityExpression": "", "objectFieldName": "", "ddmDataProviderInstanceOutput": [], "options": {"pt_BR": [{"reference":"Opção66908124","label":"Opção","value":"Opção66908124"}]}, "nativeField": false, "confirmationLabel": {"pt_BR": ""}, "fieldReference": "Text81373875", "placeholder": {"pt_BR": ""}, "dataSourceType": "manual", "direction": ["vertical"]}, "defaultValue": {"pt_BR": ""}, "fieldType": "text", "indexType": "keyword", "indexable": true, "label": {"pt_BR": "Campo de texto"}, "localizable": true, "name": "Text81373875", "nestedDataDefinitionFields": [], "readOnly": false, "repeatable": false, "required": false, "showLabel": true, "tip": {"pt_BR": ""}}], "readOnly": false, "repeatable": true, "required": false, "showLabel": true, "tip": {}}], "defaultDataLayout": {"dataLayoutFields": {}, "dataLayoutPages": [{"dataLayoutRows": [{"dataLayoutColumns": [{"columnSize": 12, "fieldNames": ["Fieldset96148159"]}]}], "description": {"pt_BR": ""}, "title": {"pt_BR": ""}}], "dataRules": [], "description": {}, "name": {"pt_BR": "Estrutura Cards"}, "paginationMode": "single-page"}, "defaultLanguageId": "pt_BR", "description": {}, "name": {"pt_BR": "Estrutura Cards"}, "storageType": "default"}